AUTHORS.rst
HISTORY.rst
Vagrantfile
calico/__init__.py
calico/__init__.pyi
calico/base.py
calico/base.pyi
calico/cli.py
calico/cli.pyi
calico/parse.py
calico/parse.pyi
docs/Makefile
docs/source/conf.py
docs/source/index.rst
docs/source/modules/base.rst
docs/source/modules/cli.rst
docs/source/modules/parse.rst
docs/source/tutorial.rst
tests/circle.c
tests/circle.yaml
tests/test_calico.py
tests/test_cli.py
tests/test_parse.py
tests/test_script.py
calico-1.2.0.dist-info/entry_points.txt
calico-1.2.0.dist-info/LICENSE.txt
calico-1.2.0.dist-info/WHEEL
calico-1.2.0.dist-info/METADATA
calico-1.2.0.dist-info/RECORD
